streamlit_book/__init__.py
streamlit_book/admin.py
streamlit_book/answers.py
streamlit_book/book_config.py
streamlit_book/chapter_config.py
streamlit_book/colored_expanders.py
streamlit_book/echo.py
streamlit_book/file_reader.py
streamlit_book/floating_button.py
streamlit_book/helpers.py
streamlit_book/keywords.py
streamlit_book/login.py
streamlit_book/render.py
streamlit_book/render_code_input.py
streamlit_book/render_multiple_choice.py
streamlit_book/render_single_choice.py
streamlit_book/render_text_input.py
streamlit_book/render_to_do_list.py
streamlit_book/render_true_or_false.py
streamlit_book/social_media.py
streamlit_book-0.7.6.dist-info/LICENSE
streamlit_book-0.7.6.dist-info/METADATA
streamlit_book-0.7.6.dist-info/WHEEL
streamlit_book-0.7.6.dist-info/top_level.txt
streamlit_book-0.7.6.dist-info/RECORD
