Metadata-Version: 2.1
Name: streamlit_book
Version: 0.7.6
Summary: A streamlit companion library to create a interactive reader for the content on a given folder.
Home-page: https://github.com/sebastiandres/streamlit_book
Author: Sebastián Flores Benner
Author-email: sebastiandres@gmail.com
License: MIT
Project-URL: Documentation, https://streamlit-book.readthedocs.io/
Project-URL: Source, https://github.com/sebastiandres/streamlit_book/
Project-URL: Tracker, https://github.com/sebastiandres/streamlit_book/issues
License-File: LICENSE
Requires-Dist: streamlit
Requires-Dist: streamlit-option-menu
